royalnet_discordpy/__init__.py
royalnet_discordpy/bullet/contents.py
royalnet_discordpy/bullet/projectiles.py
royalnet_discordpy/formatting.py
royalnet_discordpy/pda.py
royalnet_discordpy-6.6.4.dist-info/LICENSE.txt
royalnet_discordpy-6.6.4.dist-info/WHEEL
royalnet_discordpy-6.6.4.dist-info/METADATA
royalnet_discordpy-6.6.4.dist-info/RECORD
